odoo/addons/mrp_subcontracting_stock_owner_restriction/README.rst
odoo/addons/mrp_subcontracting_stock_owner_restriction/__init__.py
odoo/addons/mrp_subcontracting_stock_owner_restriction/__manifest__.py
odoo/addons/mrp_subcontracting_stock_owner_restriction/i18n/mrp_subcontracting_stock_owner_restriction.pot
odoo/addons/mrp_subcontracting_stock_owner_restriction/models/__init__.py
odoo/addons/mrp_subcontracting_stock_owner_restriction/models/mrp_production.py
odoo/addons/mrp_subcontracting_stock_owner_restriction/readme/CONTRIBUTORS.rst
odoo/addons/mrp_subcontracting_stock_owner_restriction/readme/DESCRIPTION.rst
odoo/addons/mrp_subcontracting_stock_owner_restriction/static/description/icon.png
odoo/addons/mrp_subcontracting_stock_owner_restriction/static/description/index.html
odoo/addons/mrp_subcontracting_stock_owner_restriction/tests/__init__.py
odoo/addons/mrp_subcontracting_stock_owner_restriction/tests/test_mrp_subcontracting_stock_owner_restriction.py
odoo_addon_mrp_subcontracting_stock_owner_restriction-16.0.1.0.0.2.dist-info/METADATA
odoo_addon_mrp_subcontracting_stock_owner_restriction-16.0.1.0.0.2.dist-info/WHEEL
odoo_addon_mrp_subcontracting_stock_owner_restriction-16.0.1.0.0.2.dist-info/top_level.txt
odoo_addon_mrp_subcontracting_stock_owner_restriction-16.0.1.0.0.2.dist-info/RECORD
